tests/__init__.py
tests/test_beam.py
tests/test_detector.py
tests/test_laue.py
tests/test_mesh.py
tests/test_motion.py
tests/test_phase.py
tests/test_polycrystal.py
tests/test_scattering_unit.py
tests/test_templates.py
tests/test_utils.py
xrd_simulator/__init__.py
xrd_simulator/beam.py
xrd_simulator/detector.py
xrd_simulator/laue.py
xrd_simulator/mesh.py
xrd_simulator/motion.py
xrd_simulator/phase.py
xrd_simulator/polycrystal.py
xrd_simulator/scattering_unit.py
xrd_simulator/templates.py
xrd_simulator/utils.py
xrd_simulator-0.4.1.dist-info/LICENSE
xrd_simulator-0.4.1.dist-info/METADATA
xrd_simulator-0.4.1.dist-info/WHEEL
xrd_simulator-0.4.1.dist-info/top_level.txt
xrd_simulator-0.4.1.dist-info/RECORD
