Metadata-Version: 2.1
Name: xrd-simulator
Version: 0.4.1
Summary: Tools for diffraction simulation of s3dxrd type experiments.
Home-page: https://github.com/AxelHenningsson/xrd_simulator
Author: Axel Henningsson
Author-email: nilsaxelhenningsson@gmail.com
Project-URL: Documentation, https://axelhenningsson.github.io/xrd_simulator/
Classifier: Programming Language :: Python :: 3.8
Classifier: License :: OSI Approved :: MIT License
Classifier: Operating System :: OS Independent
Requires-Python: >=3.8,<3.11
License-File: LICENSE
Requires-Dist: matplotlib
Requires-Dist: numpy
Requires-Dist: meshio
Requires-Dist: pygalmesh
Requires-Dist: scipy
Requires-Dist: numba
Requires-Dist: pycifrw
Requires-Dist: dill
Requires-Dist: xfab
Requires-Dist: netcdf4
Requires-Dist: h5py
